control_unit.v
module Control_Unit (
    input wire clk,
    input wire rst_n,
    input wire [6:0] instruction_opcode,
    output reg pc_write,
    output reg ir_write,
    output reg pc_source,
    output reg reg_write,
    output reg memory_read,
    output reg is_immediate,
    output reg memory_write,
    output reg pc_write_cond,
    output reg lorD,
    output reg memory_to_reg,
    output reg [1:0] aluop,
    output reg [1:0] alu_src_a,
    output reg [1:0] alu_src_b
);

	localparam FETCH     = 4'b0000;
	localparam DECODE    = 4'b0001;
	localparam MEMADR    = 4'b0010;
	localparam MEMREAD   = 4'b0011;
	localparam MEMWB     = 4'b0100;
	localparam MEMWRITE  = 4'b0101;
	localparam EXECUTER  = 4'b0110;
	localparam ALUWB     = 4'b0111;
	localparam EXECUTEI  = 4'b1000;
	localparam JAL       = 4'b1001;
	localparam BRANCH    = 4'b1010;
	localparam JALR      = 4'b1011;
	localparam AUIPC     = 4'b1100;
	localparam LUI       = 4'b1101;
	localparam JALR_PC   = 4'b1110; 
	localparam CSR       = 4'b1111; 
	localparam LW      = 7'b0000011;
	localparam SW      = 7'b0100011;
	localparam RTYPE   = 7'b0110011;
	localparam ITYPE   = 7'b0010011;
	localparam JALI    = 7'b1101111;
	localparam BRANCHI = 7'b1100011;
	localparam JALRI   = 7'b1100111;
	localparam AUIPCI  = 7'b0010111;
	localparam LUII    = 7'b0110111;
	localparam CSR_OP  = 7'b1110011;

	reg [3:0] state_cs, state_ns;

	always @(posedge clk or negedge rst_n) begin
	    if (!rst_n) begin
	        state_cs <= FETCH;
	    end else begin
	        state_cs <= state_ns;
	    end
	end

	always @(*) begin
	    state_ns = state_cs;
	    pc_write = 0;
	    ir_write = 0;
	    pc_source = 0;
	    reg_write = 0;
	    memory_read = 0;
	    is_immediate = 0;
	    memory_write = 0;
	    pc_write_cond = 0;
	    lorD = 0;
	    memory_to_reg = 0;
	    aluop = 2'b00;
	    alu_src_a = 2'b00;
	    alu_src_b = 2'b00;

	    case (state_cs)
	        FETCH: begin
	            pc_write = 1;
	            ir_write = 1;
	            memory_read = 1;
	            lorD = 0; 
	            alu_src_a = 2'b00; 
	            alu_src_b = 2'b01; 
	            aluop = 2'b00; 
	            state_ns = DECODE;
	        end

	        DECODE: begin
	            alu_src_a = 2'b10; 
	            alu_src_b = 2'b10; 
	            aluop = 2'b00; 

	            case (instruction_opcode)
	                RTYPE: state_ns = EXECUTER;
	                ITYPE: state_ns = EXECUTEI;
	                LW: state_ns = MEMADR;
	                SW: state_ns = MEMADR;
	                JALI: state_ns = JAL;
	                BRANCHI: state_ns = BRANCH;
	                JALRI: state_ns = JALR;
	                AUIPCI: state_ns = AUIPC;
	                LUII: state_ns = LUI;
	                CSR_OP: state_ns = CSR;
	                default: state_ns = FETCH; 
	            endcase
	        end

	        MEMADR: begin
	            aluop = 2'b00; 
	            alu_src_a = 2'b01; 
	            alu_src_b = 2'b10; 
	            is_immediate = 1; 
	            case (instruction_opcode)
	                LW: state_ns = MEMREAD;
	                SW: state_ns = MEMWRITE;
	                default: state_ns = FETCH; 
	            endcase
	        end

	        MEMREAD: begin
	            memory_read = 1;
	            lorD = 1; 
	            state_ns = MEMWB;
	        end

	        MEMWB: begin
	            reg_write = 1;
	            memory_to_reg = 1; 
	            state_ns = FETCH;
	        end

	        MEMWRITE: begin
	            memory_write = 1;
	            lorD = 1; 
	            state_ns = FETCH;
	        end

	        EXECUTER: begin
	            aluop = 2'b10; 
	            alu_src_a = 2'b01; 
	            alu_src_b = 2'b00; 
	            state_ns = ALUWB;
	        end

	        EXECUTEI: begin
	            aluop = 2'b10; 
	            alu_src_a = 2'b01; 
	            alu_src_b = 2'b10; 
	            is_immediate = 1;
	            state_ns = ALUWB;
	        end

	        ALUWB: begin
	            reg_write = 1;
	            memory_to_reg = 0; 
	            state_ns = FETCH;
	        end

	        JAL: begin
	            pc_write = 1;
	            pc_source = 2'b01; 
	            reg_write = 1;
	            aluop = 2'b00; 
	            alu_src_a = 2'b10; 
	            alu_src_b = 2'b01; 
	            state_ns = FETCH;
	        end

	        BRANCH: begin
	            pc_write_cond = 1;
	            pc_source = 2'b01; 
	            aluop = 2'b01; 
	            alu_src_a = 2'b01; 
	            alu_src_b = 2'b00; 
	            state_ns = FETCH;
	        end

	        JALR: begin
	            aluop = 2'b00; 
	            alu_src_a = 2'b01; 
	            alu_src_b = 2'b10; 
	            is_immediate = 1;
	            state_ns = JALR_PC;
	        end

	        JALR_PC: begin 
	            pc_write = 1;
	            pc_source = 2'b10; 
	            reg_write = 1; 
	            aluop = 2'b00; 
	            alu_src_a = 2'b00; 
	            alu_src_b = 2'b01; 
	            state_ns = FETCH;
	        end

	        AUIPC: begin
	            reg_write = 1;
	            aluop = 2'b00; 
	            alu_src_a = 2'b00; 
	            alu_src_b = 2'b10; 
	            is_immediate = 1;
	            state_ns = ALUWB;
	        end

	        LUI: begin
	            reg_write = 1;
	            aluop = 2'b00; 
	            alu_src_a = 2'b11; 
	            alu_src_b = 2'b10; 
	            is_immediate = 1;
	            state_ns = ALUWB;
	        end

	        CSR: begin
	            reg_write = 1;
	            memory_to_reg = 10; 
	            state_ns = FETCH;
	        end

	        default: begin
	            state_ns = FETCH;
	        end
	    endcase
	end
	
endmodule

tb.v
`timescale 1ns/1ps

module tb();


reg clk = 0;
reg rst_n;
reg [6:0] instruction_opcode;
wire pc_write;
wire ir_write;
wire pc_source;
wire reg_write;
wire memory_read;
wire is_immediate;
wire memory_write;
wire pc_write_cond;
wire lorD;
wire memory_to_reg;
wire [1:0] aluop;
wire [1:0] alu_src_a;
wire [1:0] alu_src_b;

reg expected_pc_write;
reg expected_ir_write;
reg expected_pc_source;
reg expected_reg_write;
reg expected_memory_read;
reg expected_is_immediate;
reg expected_memory_write;
reg expected_pc_write_cond;
reg expected_lorD;
reg expected_memory_to_reg;
reg [1:0] expected_aluop;
reg [1:0] expected_alu_src_a;
reg [1:0] expected_alu_src_b;

reg [22:0] file_data [0:4];
// 0110011_0_0_0_1_0_0_0_0_0_0_00_00_00 7+10+2+2+2 = 23 bits

// Instruction Opcodes
localparam LW      = 7'b0000011;
localparam SW      = 7'b0100011;
localparam RTYPE   = 7'b0110011;
localparam ITYPE   = 7'b0010011;
localparam JALI    = 7'b1101111;
localparam BRANCHI = 7'b1100011;
localparam JALRI   = 7'b1100111;
localparam AUIPCI  = 7'b0010111;
localparam LUII    = 7'b0110111;
localparam CSR     = 7'b1110011;

Control_Unit c_un(
    .clk(clk),
    .rst_n(rst_n),
    .instruction_opcode(instruction_opcode),
    .pc_write(pc_write),
    .ir_write(ir_write),
    .pc_source(pc_source),
    .reg_write(reg_write),
    .memory_read(memory_read),
    .is_immediate(is_immediate),
    .memory_write(memory_write),
    .pc_write_cond(pc_write_cond),
    .lorD(lorD),
    .memory_to_reg(memory_to_reg),
    .aluop(aluop),
    .alu_src_a(alu_src_a),
    .alu_src_b(alu_src_b)
);

always #1 clk = ~clk;

integer i;
integer j;

initial begin
    $dumpfile("saida.vcd");
    $dumpvars(0, tb);
    $readmemb("teste.txt", file_data);
    
    instruction_opcode = file_data[0][22:16];

    case (instruction_opcode)
        LW      : j=5;
        SW      : j=4;
        RTYPE   : j=4;
        ITYPE   : j=4;
        JALI    : j=4;
        BRANCHI : j=3;
        JALRI   : j=5;
        AUIPCI  : j=4;
        LUII    : j=4;
        default : j=0;
    endcase

    rst_n = 1'b0;
    #4
    rst_n = 1'b1;
    
    for (i=0; i<j; i++) begin

        expected_pc_write       = file_data[i][15];
        expected_ir_write       = file_data[i][14];
        expected_pc_source      = file_data[i][13];
        expected_reg_write      = file_data[i][12];
        expected_memory_read    = file_data[i][11];
        expected_is_immediate   = file_data[i][10];
        expected_memory_write   = file_data[i][9];
        expected_pc_write_cond  = file_data[i][8];
        expected_lorD           = file_data[i][7];
        expected_memory_to_reg  = file_data[i][6];
        expected_aluop          = file_data[i][5:4];
        expected_alu_src_a      = file_data[i][3:2];
        expected_alu_src_b      = file_data[i][1:0];

        if (pc_write        === expected_pc_write       &&
            ir_write        === expected_ir_write       &&
            pc_source       === expected_pc_source      &&
            reg_write       === expected_reg_write      &&
            memory_read     === expected_memory_read    &&
            is_immediate    === expected_is_immediate   &&
            memory_write    === expected_memory_write   &&
            pc_write_cond   === expected_pc_write_cond  &&
            lorD            === expected_lorD           &&
            memory_to_reg   === expected_memory_to_reg  &&
            aluop           === expected_aluop          &&
            alu_src_a       === expected_alu_src_a      &&
            alu_src_b       === expected_alu_src_b ) begin
                $display("=== OK ",
                    "Ciclo na FSM = ", i,
                    "\nopcode = ", instruction_opcode, 
                    " pc_write = ", pc_write, 
                    " ir_write = ", ir_write, 
                    " pc_source = ", pc_source, 
                    " reg_write = ", reg_write, 
                    " memory_read = ", memory_read, 
                    " is_immediate = ", is_immediate, 
                    " memory_write = ", memory_write, 
                    " pc_write_cond = ", pc_write_cond, 
                    " lorD = ", lorD, 
                    " memory_to_reg = ", memory_to_reg, 
                    " aluop = ", aluop, 
                    " alu_src_a = ", alu_src_a, 
                    " alu_src_b = ", alu_src_b);
            end else begin
                $display("=== ERRO ",
                    "Ciclo na FSM = ", i,
                    "\nopcode = ", instruction_opcode, 
                    " pc_write = ", pc_write, 
                    " ir_write = ", ir_write, 
                    " pc_source = ", pc_source, 
                    " reg_write = ", reg_write, 
                    " memory_read = ", memory_read, 
                    " is_immediate = ", is_immediate, 
                    " memory_write = ", memory_write, 
                    " pc_write_cond = ", pc_write_cond, 
                    " lorD = ", lorD, 
                    " memory_to_reg = ", memory_to_reg, 
                    " aluop = ", aluop, 
                    " alu_src_a = ", alu_src_a, 
                    " alu_src_b = ", alu_src_b,
                    "\n Esperado:\n",
                    "opcode = ", instruction_opcode,
                    " pc_write = ", expected_pc_write,
                    " ir_write = ", expected_ir_write,
                    " pc_source = ", expected_pc_source,
                    " reg_write = ", expected_reg_write,
                    " memory_read = ", expected_memory_read,
                    " is_immediate = ", expected_is_immediate,
                    " memory_write = ", expected_memory_write,
                    " pc_write_cond = ", expected_pc_write_cond,
                    " lorD = ", expected_lorD,
                    " memory_to_reg = ", expected_memory_to_reg,
                    " aluop = ", expected_aluop,
                    " alu_src_a = ", expected_alu_src_a,
                    " alu_src_b = ", expected_alu_src_b);
            end
        #2;

    end
    
    $finish;


end

endmodule

test/saida6.vcd
$date
	Wed Jul 23 03:10:50 2025
$end
$version
	Icarus Verilog
$end
$timescale
	1ps
$end
$scope module tb $end
$var wire 1 ! reg_write $end
$var wire 1 " pc_write_cond $end
$var wire 1 # pc_write $end
$var wire 1 $ pc_source $end
$var wire 1 % memory_write $end
$var wire 1 & memory_to_reg $end
$var wire 1 ' memory_read $end
$var wire 1 ( lorD $end
$var wire 1 ) is_immediate $end
$var wire 1 * ir_write $end
$var wire 2 + aluop [1:0] $end
$var wire 2 , alu_src_b [1:0] $end
$var wire 2 - alu_src_a [1:0] $end
$var parameter 7 . AUIPCI $end
$var parameter 7 / BRANCHI $end
$var parameter 7 0 CSR $end
$var parameter 7 1 ITYPE $end
$var parameter 7 2 JALI $end
$var parameter 7 3 JALRI $end
$var parameter 7 4 LUII $end
$var parameter 7 5 LW $end
$var parameter 7 6 RTYPE $end
$var parameter 7 7 SW $end
$var reg 1 8 clk $end
$var reg 2 9 expected_alu_src_a [1:0] $end
$var reg 2 : expected_alu_src_b [1:0] $end
$var reg 2 ; expected_aluop [1:0] $end
$var reg 1 < expected_ir_write $end
$var reg 1 = expected_is_immediate $end
$var reg 1 > expected_lorD $end
$var reg 1 ? expected_memory_read $end
$var reg 1 @ expected_memory_to_reg $end
$var reg 1 A expected_memory_write $end
$var reg 1 B expected_pc_source $end
$var reg 1 C expected_pc_write $end
$var reg 1 D expected_pc_write_cond $end
$var reg 1 E expected_reg_write $end
$var reg 7 F instruction_opcode [6:0] $end
$var reg 1 G rst_n $end
$var integer 32 H i [31:0] $end
$var integer 32 I j [31:0] $end
$scope module c_un $end
$var wire 1 8 clk $end
$var wire 7 J instruction_opcode [6:0] $end
$var wire 1 G rst_n $end
$var parameter 4 K ALUWB $end
$var parameter 4 L AUIPC $end
$var parameter 7 M AUIPCI $end
$var parameter 4 N BRANCH $end
$var parameter 7 O BRANCHI $end
$var parameter 4 P CSR $end
$var parameter 7 Q CSR_OP $end
$var parameter 4 R DECODE $end
$var parameter 4 S EXECUTEI $end
$var parameter 4 T EXECUTER $end
$var parameter 4 U FETCH $end
$var parameter 7 V ITYPE $end
$var parameter 4 W JAL $end
$var parameter 7 X JALI $end
$var parameter 4 Y JALR $end
$var parameter 7 Z JALRI $end
$var parameter 4 [ JALR_PC $end
$var parameter 4 \ LUI $end
$var parameter 7 ] LUII $end
$var parameter 7 ^ LW $end
$var parameter 4 _ MEMADR $end
$var parameter 4 ` MEMREAD $end
$var parameter 4 a MEMWB $end
$var parameter 4 b MEMWRITE $end
$var parameter 7 c RTYPE $end
$var parameter 7 d SW $end
$var reg 2 e alu_src_a [1:0] $end
$var reg 2 f alu_src_b [1:0] $end
$var reg 2 g aluop [1:0] $end
$var reg 1 * ir_write $end
$var reg 1 ) is_immediate $end
$var reg 1 ( lorD $end
$var reg 1 ' memory_read $end
$var reg 1 & memory_to_reg $end
$var reg 1 % memory_write $end
$var reg 1 $ pc_source $end
$var reg 1 # pc_write $end
$var reg 1 " pc_write_cond $end
$var reg 1 ! reg_write $end
$var reg 4 h state_cs [3:0] $end
$var reg 4 i state_ns [3:0] $end
$upscope $end
$upscope $end
$enddefinitions $end
$comment Show the parameter values. $end
$dumpall
b100011 d
b110011 c
b101 b
b100 a
b11 `
b10 _
b11 ^
b110111 ]
b1101 \
b1110 [
b1100111 Z
b1011 Y
b1101111 X
b1001 W
b10011 V
b0 U
b110 T
b1000 S
b1 R
b1110011 Q
b1111 P
b1100011 O
b1010 N
b10111 M
b1100 L
b111 K
b100011 7
b110011 6
b11 5
b110111 4
b1100111 3
b1101111 2
b10011 1
b1110011 0
b1100011 /
b10111 .
$end
#0
$dumpvars
b1 i
b0 h
b0 g
b1 f
b0 e
b110111 J
b100 I
bx H
0G
b110111 F
xE
xD
xC
xB
xA
x@
x?
x>
x=
x<
bx ;
bx :
bx 9
08
b0 -
b1 ,
b0 +
1*
0)
0(
1'
0&
0%
0$
1#
0"
0!
$end
#1000
18
#2000
08
#3000
18
#4000
08
b1 :
b0 9
b0 ;
0@
0>
0D
0A
0=
1?
0E
0B
1<
1C
b0 H
1G
#5000
b1101 i
b10 -
b10 e
b10 ,
b10 f
0'
0*
0#
b1 h
18
#6000
08
b10 :
b10 9
0?
0<
0C
b1 H
#7000
b111 i
1)
1!
b10 ,
b10 f
b11 -
b11 e
b1101 h
18
#8000
08
b11 9
b10 H
#9000
b0 i
b0 ,
b0 f
b0 -
b0 e
0)
1!
b111 h
18
#10000
08
b0 :
b0 9
1E
b11 H
#11000
b1 i
b1 ,
b1 f
1'
1*
1#
0!
b0 h
18
#12000
08
b100 H
